hours/__init__.py
hours/cli.py
hours/config.py
hours/controller.py
hours/date_utils.py
hours/model.py
hours/views.py
hours-0.3.1.dist-info/METADATA
hours-0.3.1.dist-info/WHEEL
hours-0.3.1.dist-info/entry_points.txt
hours-0.3.1.dist-info/RECORD
